[{"__type__":"cc.SpriteFrame","content":{"name":"wifi-0","texture":"47ae7QwY5FFqsL7GoyHxCC","rect":[1373,869,55,48],"offset":[0,0],"originalSize":[59,52],"capInsets":[0,0,0,0]}},{"__type__":"cc.SpriteFrame","content":{"name":"lb_list_pointer","texture":"47ae7QwY5FFqsL7GoyHxCC","rect":[1228,333,23,16],"offset":[0,0],"originalSize":[25,18],"capInsets":[0,0,0,0]}},{"__type__":"cc.SpriteFrame","content":{"name":"stg_icon_sansang","texture":"47ae7QwY5FFqsL7GoyHxCC","rect":[1374,1068,40,39],"offset":[0,0],"originalSize":[40,39],"capInsets":[0,0,0,0]}},{"__type__":"cc.SpriteFrame","content":{"name":"lb_download_circle","texture":"47ae7QwY5FFqsL7GoyHxCC","rect":[1327,0,128,127],"offset":[0,0],"originalSize":[128,127],"capInsets":[0,0,0,0]}},{"__type__":"cc.SpriteFrame","content":{"name":"ngchoi1","texture":"47ae7QwY5FFqsL7GoyHxCC","rect":[1490,272,26,31],"offset":[0,0],"originalSize":[28,33],"capInsets":[0,0,0,0]}},{"__type__":"cc.SpriteFrame","content":{"name":"stg_icon_rung","texture":"47ae7QwY5FFqsL7GoyHxCC","rect":[1238,1068,50,39],"offset":[0,0],"originalSize":[50,39],"capInsets":[0,0,0,0]}},{"__type__":"cc.SpriteFrame","content":{"name":"iap","texture":"47ae7QwY5FFqsL7GoyHxCC","rect":[1273,1281,80,97],"offset":[-1,0],"originalSize":[110,99],"capInsets":[0,0,0,0]}},{"__type__":"cc.SpriteAtlas","_name":"lobby.plist","_spriteFrames":{"banner0":{"__uuid__":"94yXTeKldGu61tStm1odCt"},"bottom":{"__uuid__":"fdB+cZQGtKA75+TkfDDAlA"},"chat_khung_emo":{"__uuid__":"60JgnSsvBFcrbhNVGRpVj+"},"chat_khung_noidung":{"__uuid__":"e2n/5iveRN4ZoALwOBwFV4"},"chuyengold_bg_tien":{"__uuid__":"c7yHSpki9PzbpNdBMERvVo"},"dl_chu":{"__uuid__":"9cDtv9HVVD8ZQ8H341NXzm"},"download_app":{"__uuid__":"a50//VmpFC8r8tgjEj/uGI"},"dt_line":{"__uuid__":"1a2YIW3XZPTLcQGl7FKEDi"},"edit_box2":{"__uuid__":"c8Knk9bsNBfpOgod1yejjN"},"iap":{"__uuid__":"13rx1c+bBBHZWbZvf32Pvp"},"icon_vang":{"__uuid__":"e5GRWrfuxJDYTAFmJyFbOr"},"icon_vang_small":{"__uuid__":"fc8ZEhP4lD9YaIznFkJzX1"},"khung_avatar_2":{"__uuid__":"b4XqwWTtxNfoAxF9mLJIt6"},"khung_chatnhanh":{"__uuid__":"eaE6PvMPVNiJ3EVPoxRv9s"},"khung_muccuoc":{"__uuid__":"76ZymVpKRFM4Zl/Cqmdu8C"},"khung_muccuoc_chon":{"__uuid__":"c450p8rfdCIqjTKFedisVQ"},"khung_tien":{"__uuid__":"48YsnZFFtFGrLEDMOCeDWk"},"khung_tien2":{"__uuid__":"f5sgRH4URC7J/4We2+OtZA"},"lb_banner_dot":{"__uuid__":"b6BQ0PGItJ2KVSFEE6a05g"},"lb_banner_frame":{"__uuid__":"efN2kQSxJO/pPPLVOjFL7l"},"lb_download_circle":{"__uuid__":"0aMFwKHBVFU7oHI5gDcIoB"},"lb_download_circle_bg":{"__uuid__":"31iAv1n1JD+L1mTKcRuVyu"},"lb_edit_box":{"__uuid__":"6axCt/d9tPp6SWl4aLxLlY"},"lb_floating_text_bg":{"__uuid__":"53BOTJ1rhIFJuyqBglDYJ2"},"lb_footer":{"__uuid__":"5bppEUJCNJT5VU2ZcU0SL9"},"lb_game_category":{"__uuid__":"80NbohR11Kua7+1IYYqFmg"},"lb_header_left":{"__uuid__":"35gfSk4HxGaIsb3j4KUUpN"},"lb_header_right":{"__uuid__":"4dcsnw6KlK17oE0m0o+9nZ"},"lb_icon_rank_1":{"__uuid__":"18/CdJa45KwLgf9uHIIUfj"},"lb_icon_rank_2":{"__uuid__":"92D9KO19pFErFloGwU3kfZ"},"lb_icon_rank_3":{"__uuid__":"214/XgSqlLirqbzR9vqVG5"},"lb_invite_bg":{"__uuid__":"50hSWugIBKW7lAG2CA6Eay"},"lb_khung_ten":{"__uuid__":"d8+iOM1pxFX6JIS8fStZ8a"},"lb_list_pointer":{"__uuid__":"03FbMnl8VNZL+bBeMKBzSe"},"lb_loading_spin":{"__uuid__":"b8Kiky28dO84SxIV+g0Kas"},"lb_loading_spin2":{"__uuid__":"e6y+/9Nu1MDY5s/E9HcgW/"},"lb_loading_spin_logo":{"__uuid__":"62PNMZrEBPabJzRzx9sE2p"},"lb_loading_spin_logo2":{"__uuid__":"31+rAB8aNDEqOZ6ndj3vvy"},"lb_logo_header":{"__uuid__":"d9SViBDCtPhqp2Gv//hdRr"},"lb_mail_bg":{"__uuid__":"45PpQfWRpOK6DkXasAvh0K"},"lb_popup_title_bg_1":{"__uuid__":"d7tACSgaJI4qGrZl2FGa0F"},"lb_popup_title_bg_2":{"__uuid__":"9eqh/Lgx9ON6k+ur7dQAkV"},"lb_quenmk_text":{"__uuid__":"4cj0upd9BAaaZYTnam/CDk"},"lb_thanh_bar":{"__uuid__":"702jZmE7pCmLDVBTeHlmxq"},"ngchoi0":{"__uuid__":"1aKPTJUHlJzq1bEhn+rumn"},"ngchoi1":{"__uuid__":"0abjAA419I2btsB8fcChQ2"},"notifi":{"__uuid__":"58VhL3w7JIrIQooPVlVw3R"},"popup_1":{"__uuid__":"1er6dSCTdI+6Wb8INlj5wD"},"popup_2":{"__uuid__":"af+xNhvPVKYraxsuNzIHWn"},"popup_3":{"__uuid__":"8dxujLUFdDFb+iXTQXyYCf"},"popup_nt_bg_label":{"__uuid__":"53If8bTgNBBLR5+zms9T34"},"setting_line":{"__uuid__":"3dQaeKYl9KLbJLxCtueAhS"},"solo_check":{"__uuid__":"be1mLRgoVMUJeS5L4a8rvY"},"solo_checked":{"__uuid__":"83ppJ1jg9PKbgqqWu7J1zo"},"stg_icon_amthanh":{"__uuid__":"80WySDxqhL1od9X0aS+Ztj"},"stg_icon_banchoi":{"__uuid__":"a5V6SVY1JFNo9Miqfr+moj"},"stg_icon_moichoi":{"__uuid__":"52FAkTPEZDKJC85o8Rw+Ms"},"stg_icon_rung":{"__uuid__":"0fTeE4lmRGYLOr4nIhU5JP"},"stg_icon_sansang":{"__uuid__":"04DencOJFOzZb7trGUK1DD"},"top_line":{"__uuid__":"521ysaCv1B3YEoAKLsoBvq"},"wifi-0":{"__uuid__":"02/h8J591EfJPmcjMgR4y6"},"wifi-1":{"__uuid__":"e8zhsqpJJNUJ9VgS8/cHYt"},"wifi-2":{"__uuid__":"1dphhThlVFQabGSGf6JXN/"},"wifi-3":{"__uuid__":"abmY9cotBGLZXcSHKmYQn/"}}},{"__type__":"cc.SpriteFrame","content":{"name":"lb_icon_rank_1","texture":"47ae7QwY5FFqsL7GoyHxCC","rect":[1441,146,57,65],"offset":[0,0],"originalSize":[57,65],"capInsets":[0,0,0,0]}},{"__type__":"cc.SpriteFrame","content":{"name":"ngchoi0","texture":"47ae7QwY5FFqsL7GoyHxCC","rect":[1490,305,24,29],"offset":[0,0],"originalSize":[26,31],"capInsets":[0,0,0,0]}},{"__type__":"cc.SpriteFrame","content":{"name":"dt_line","texture":"47ae7QwY5FFqsL7GoyHxCC","rect":[1500,146,4,50],"offset":[0,0],"originalSize":[4,50],"capInsets":[0,0,0,0]}},{"__type__":"cc.SpriteFrame","content":{"name":"wifi-2","texture":"47ae7QwY5FFqsL7GoyHxCC","rect":[1330,1380,55,48],"offset":[0,0],"originalSize":[59,52],"capInsets":[0,0,0,0]}},{"__type__":"cc.SpriteFrame","content":{"name":"popup_1","texture":"47ae7QwY5FFqsL7GoyHxCC","rect":[0,686,694,501],"offset":[0,0],"originalSize":[694,501],"capInsets":[0,0,0,0]}},{"__type__":"cc.SpriteFrame","content":{"name":"lb_icon_rank_3","texture":"47ae7QwY5FFqsL7GoyHxCC","rect":[1436,272,52,59],"offset":[0,0],"originalSize":[52,59],"capInsets":[0,0,0,0]}},{"__type__":"cc.SpriteFrame","content":{"name":"lb_download_circle_bg","texture":"47ae7QwY5FFqsL7GoyHxCC","rect":[1249,774,122,122],"offset":[0,0],"originalSize":[122,122],"capInsets":[0,0,0,0]}},{"__type__":"cc.SpriteFrame","content":{"name":"lb_loading_spin_logo2","texture":"47ae7QwY5FFqsL7GoyHxCC","rect":[1427,1281,34,35],"offset":[0,0],"originalSize":[34,35],"capInsets":[0,0,0,0]}},{"__type__":"cc.SpriteFrame","content":{"name":"lb_header_left","texture":"47ae7QwY5FFqsL7GoyHxCC","rect":[696,804,540,123],"offset":[-2,0],"originalSize":[544,123],"capInsets":[0,0,0,0]}},{"__type__":"cc.SpriteFrame","content":{"name":"setting_line","texture":"47ae7QwY5FFqsL7GoyHxCC","rect":[674,1336,499,1],"offset":[6,0],"originalSize":[551,3],"capInsets":[0,0,0,0]}},{"__type__":"cc.SpriteFrame","content":{"name":"lb_mail_bg","texture":"47ae7QwY5FFqsL7GoyHxCC","rect":[966,1357,201,53],"offset":[0,0],"originalSize":[201,53],"capInsets":[0,0,0,0]}},{"__type__":"cc.SpriteFrame","content":{"name":"khung_tien","texture":"47ae7QwY5FFqsL7GoyHxCC","rect":[1183,272,251,59],"offset":[0,0],"originalSize":[251,59],"capInsets":[0,0,0,0]}},{"__type__":"cc.SpriteFrame","content":{"name":"lb_quenmk_text","texture":"47ae7QwY5FFqsL7GoyHxCC","rect":[400,1410,194,30],"offset":[0,0],"originalSize":[194,30],"capInsets":[0,0,0,0]}},{"__type__":"cc.SpriteFrame","content":{"name":"lb_header_right","texture":"47ae7QwY5FFqsL7GoyHxCC","rect":[696,1013,540,96],"offset":[2,13],"originalSize":[544,123],"capInsets":[0,0,0,0]}},{"__type__":"cc.SpriteFrame","content":{"name":"lb_invite_bg","texture":"47ae7QwY5FFqsL7GoyHxCC","rect":[1183,146,256,70],"offset":[0,0],"originalSize":[256,70],"capInsets":[0,0,0,0]}},{"__type__":"cc.SpriteFrame","content":{"name":"stg_icon_moichoi","texture":"47ae7QwY5FFqsL7GoyHxCC","rect":[1095,774,38,28],"offset":[-1,0],"originalSize":[40,39],"capInsets":[0,0,0,0]}},{"__type__":"cc.SpriteFrame","content":{"name":"top_line","texture":"47ae7QwY5FFqsL7GoyHxCC","rect":[1238,804,5,71],"offset":[0,0],"originalSize":[5,71],"capInsets":[0,0,0,0]}},{"__type__":"cc.SpriteFrame","content":{"name":"lb_floating_text_bg","texture":"47ae7QwY5FFqsL7GoyHxCC","rect":[400,1357,564,51],"offset":[0,0],"originalSize":[564,51],"capInsets":[0,0,0,0]}},{"__type__":"cc.SpriteFrame","content":{"name":"popup_nt_bg_label","texture":"47ae7QwY5FFqsL7GoyHxCC","rect":[596,1410,158,34],"offset":[0,0],"originalSize":[158,34],"capInsets":[0,0,0,0]}},{"__type__":"cc.SpriteFrame","content":{"name":"notifi","texture":"47ae7QwY5FFqsL7GoyHxCC","rect":[1416,1068,39,39],"offset":[0,0],"originalSize":[39,39],"capInsets":[0,0,0,0]}},{"__type__":"cc.SpriteFrame","content":{"name":"lb_footer","texture":"47ae7QwY5FFqsL7GoyHxCC","rect":[0,1189,1271,89],"offset":[0,0],"originalSize":[1271,89],"capInsets":[0,0,0,0]}},{"__type__":"cc.SpriteFrame","content":{"name":"chat_khung_emo","texture":"47ae7QwY5FFqsL7GoyHxCC","rect":[1273,1189,90,90],"offset":[0,0],"originalSize":[90,90],"capInsets":[0,0,0,0]}},{"__type__":"cc.SpriteFrame","content":{"name":"lb_loading_spin_logo","texture":"47ae7QwY5FFqsL7GoyHxCC","rect":[1373,774,96,93],"offset":[3,-1],"originalSize":[102,105],"capInsets":[0,0,0,0]}},{"__type__":"cc.SpriteFrame","content":{"name":"lb_edit_box","texture":"47ae7QwY5FFqsL7GoyHxCC","rect":[1183,218,330,52],"offset":[0,0],"originalSize":[338,67],"capInsets":[0,0,0,0]}},{"__type__":"cc.SpriteFrame","content":{"name":"lb_thanh_bar","texture":"47ae7QwY5FFqsL7GoyHxCC","rect":[1173,1111,265,40],"offset":[0,0],"originalSize":[265,40],"capInsets":[0,0,0,0]}},{"__type__":"cc.SpriteFrame","content":{"name":"khung_muccuoc","texture":"47ae7QwY5FFqsL7GoyHxCC","rect":[696,352,283,450],"offset":[0,0],"originalSize":[285,452],"capInsets":[0,0,0,0]}},{"__type__":"cc.SpriteFrame","content":{"name":"lb_game_category","texture":"47ae7QwY5FFqsL7GoyHxCC","rect":[1466,929,52,410],"offset":[0,0],"originalSize":[52,410],"capInsets":[0,0,0,0]}},{"__type__":"cc.SpriteFrame","content":{"name":"stg_icon_amthanh","texture":"47ae7QwY5FFqsL7GoyHxCC","rect":[1135,774,36,28],"offset":[-1,0],"originalSize":[40,39],"capInsets":[0,0,0,0]}},{"__type__":"cc.SpriteFrame","content":{"name":"solo_checked","texture":"47ae7QwY5FFqsL7GoyHxCC","rect":[1466,1341,43,43],"offset":[0,0],"originalSize":[43,43],"capInsets":[0,0,0,0]}},{"__type__":"cc.SpriteFrame","content":{"name":"popup_3","texture":"47ae7QwY5FFqsL7GoyHxCC","rect":[696,0,485,350],"offset":[0,0],"originalSize":[485,350],"capInsets":[0,0,0,0]}},{"__type__":"cc.SpriteFrame","content":{"name":"lb_icon_rank_2","texture":"47ae7QwY5FFqsL7GoyHxCC","rect":[1457,74,54,62],"offset":[0,0],"originalSize":[54,62],"capInsets":[0,0,0,0]}},{"__type__":"cc.SpriteFrame","content":{"name":"banner0","texture":"47ae7QwY5FFqsL7GoyHxCC","rect":[1249,352,266,420],"offset":[0,0],"originalSize":[266,420],"capInsets":[0,0,0,0]}},{"__type__":"cc.SpriteFrame","content":{"name":"dl_chu","texture":"47ae7QwY5FFqsL7GoyHxCC","rect":[1222,1280,49,49],"offset":[0,0],"originalSize":[49,49],"capInsets":[0,0,0,0]}},{"__type__":"cc.SpriteFrame","content":{"name":"lb_popup_title_bg_2","texture":"47ae7QwY5FFqsL7GoyHxCC","rect":[696,929,768,82],"offset":[0,0],"originalSize":[768,82],"capInsets":[0,0,0,0]}},{"__type__":"cc.SpriteFrame","content":{"name":"stg_icon_banchoi","texture":"47ae7QwY5FFqsL7GoyHxCC","rect":[1183,333,43,17],"offset":[0,0],"originalSize":[43,17],"capInsets":[0,0,0,0]}},{"__type__":"cc.SpriteFrame","content":{"name":"download_app","texture":"47ae7QwY5FFqsL7GoyHxCC","rect":[981,774,112,26],"offset":[0,0],"originalSize":[112,26],"capInsets":[0,0,0,0]}},{"__type__":"cc.SpriteFrame","content":{"name":"wifi-3","texture":"47ae7QwY5FFqsL7GoyHxCC","rect":[1273,1380,55,48],"offset":[0,0],"originalSize":[59,52],"capInsets":[0,0,0,0]}},{"__type__":"cc.SpriteFrame","content":{"name":"popup_2","texture":"47ae7QwY5FFqsL7GoyHxCC","rect":[0,0,694,684],"offset":[0,0],"originalSize":[694,684],"capInsets":[0,0,0,0]}},{"__type__":"cc.SpriteFrame","content":{"name":"khung_avatar_2","texture":"47ae7QwY5FFqsL7GoyHxCC","rect":[1169,1357,85,85],"offset":[0,0],"originalSize":[85,85],"capInsets":[0,0,0,0]}},{"__type__":"cc.SpriteFrame","content":{"name":"lb_banner_dot","texture":"47ae7QwY5FFqsL7GoyHxCC","rect":[1253,333,12,12],"offset":[0,0],"originalSize":[12,12],"capInsets":[0,0,0,0]}},{"__type__":"cc.SpriteFrame","content":{"name":"lb_loading_spin","texture":"47ae7QwY5FFqsL7GoyHxCC","rect":[1183,0,142,144],"offset":[0,0],"originalSize":[142,144],"capInsets":[0,0,0,0]}},{"__type__":"cc.SpriteFrame","content":{"name":"solo_check","texture":"47ae7QwY5FFqsL7GoyHxCC","rect":[1332,1068,40,40],"offset":[0,0],"originalSize":[40,40],"capInsets":[0,0,0,0]}},{"__type__":"cc.SpriteFrame","content":{"name":"khung_muccuoc_chon","texture":"47ae7QwY5FFqsL7GoyHxCC","rect":[674,1280,244,54],"offset":[0,0],"originalSize":[244,54],"capInsets":[0,0,0,0]}},{"__type__":"cc.SpriteFrame","content":{"name":"chuyengold_bg_tien","texture":"47ae7QwY5FFqsL7GoyHxCC","rect":[0,1280,672,75],"offset":[0,0],"originalSize":[672,75],"capInsets":[0,0,0,0]}},{"__type__":"cc.SpriteFrame","content":{"name":"edit_box2","texture":"47ae7QwY5FFqsL7GoyHxCC","rect":[1471,774,34,76],"offset":[0,0],"originalSize":[34,76],"capInsets":[0,0,0,0]}},{"__type__":"cc.SpriteFrame","content":{"name":"lb_popup_title_bg_1","texture":"47ae7QwY5FFqsL7GoyHxCC","rect":[0,1357,398,81],"offset":[0,0],"originalSize":[398,81],"capInsets":[0,0,0,0]}},{"__type__":"cc.SpriteFrame","content":{"name":"lb_khung_ten","texture":"47ae7QwY5FFqsL7GoyHxCC","rect":[1238,1013,201,53],"offset":[0,0],"originalSize":[201,53],"capInsets":[0,0,0,0]}},{"__type__":"cc.SpriteFrame","content":{"name":"lb_logo_header","texture":"47ae7QwY5FFqsL7GoyHxCC","rect":[1355,1281,70,80],"offset":[0,0],"originalSize":[70,80],"capInsets":[0,0,0,0]}},{"__type__":"cc.SpriteFrame","content":{"name":"chat_khung_noidung","texture":"47ae7QwY5FFqsL7GoyHxCC","rect":[1290,1068,40,40],"offset":[0,0],"originalSize":[40,40],"capInsets":[0,0,0,0]}},{"__type__":"cc.SpriteFrame","content":{"name":"icon_vang","texture":"47ae7QwY5FFqsL7GoyHxCC","rect":[1365,1189,68,89],"offset":[0,0],"originalSize":[68,89],"capInsets":[0,0,0,0]}},{"__type__":"cc.SpriteFrame","content":{"name":"lb_loading_spin2","texture":"47ae7QwY5FFqsL7GoyHxCC","rect":[1387,1380,47,48],"offset":[0,0],"originalSize":[47,48],"capInsets":[0,0,0,0]}},{"__type__":"cc.SpriteFrame","content":{"name":"wifi-1","texture":"47ae7QwY5FFqsL7GoyHxCC","rect":[1430,869,55,48],"offset":[0,0],"originalSize":[59,52],"capInsets":[0,0,0,0]}},{"__type__":"cc.SpriteFrame","content":{"name":"khung_chatnhanh","texture":"47ae7QwY5FFqsL7GoyHxCC","rect":[920,1280,300,42],"offset":[0,0],"originalSize":[300,42],"capInsets":[0,0,0,0]}},{"__type__":"cc.SpriteFrame","content":{"name":"lb_banner_frame","texture":"47ae7QwY5FFqsL7GoyHxCC","rect":[981,352,266,420],"offset":[0,0],"originalSize":[266,420],"capInsets":[0,0,0,0]}},{"__type__":"cc.SpriteFrame","content":{"name":"khung_tien2","texture":"47ae7QwY5FFqsL7GoyHxCC","rect":[696,1111,475,75],"offset":[0,0],"originalSize":[475,75],"capInsets":[0,0,0,0]}},{"__type__":"cc.SpriteFrame","content":{"name":"icon_vang_small","texture":"47ae7QwY5FFqsL7GoyHxCC","rect":[1457,0,55,72],"offset":[0,0],"originalSize":[55,72],"capInsets":[0,0,0,0]}},{"__type__":"cc.SpriteFrame","content":{"name":"bottom","texture":"47ae7QwY5FFqsL7GoyHxCC","rect":[1253,347,2,2],"offset":[-639,45],"originalSize":[1280,92],"capInsets":[0,0,0,0]}}]